{
	"configurations" : 
	[
		{
			"directories" : 
			[
				{
					"build" : ".",
					"childIndexes" : 
					[
						1,
						5,
						7,
						9
					],
					"jsonFile" : "directory-.-Debug-d0094a50bb2071803777.json",
					"minimumCMakeVersion" : 
					{
						"string" : "3.21"
					},
					"projectIndex" : 0,
					"source" : ".",
					"targetIndexes" : 
					[
						0,
						11
					]
				},
				{
					"build" : "interpreter",
					"childIndexes" : 
					[
						2,
						3,
						4
					],
					"jsonFile" : "directory-interpreter-Debug-ca7d5bde384c7024ebdc.json",
					"minimumCMakeVersion" : 
					{
						"string" : "3.21"
					},
					"parentIndex" : 0,
					"projectIndex" : 1,
					"source" : "interpreter",
					"targetIndexes" : 
					[
						1
					]
				},
				{
					"build" : "interpreter/lexer",
					"jsonFile" : "directory-interpreter.lexer-Debug-67a70c55d324c48a79e6.json",
					"minimumCMakeVersion" : 
					{
						"string" : "3.21"
					},
					"parentIndex" : 1,
					"projectIndex" : 2,
					"source" : "interpreter/lexer",
					"targetIndexes" : 
					[
						2,
						14
					]
				},
				{
					"build" : "interpreter/tests",
					"jsonFile" : "directory-interpreter.tests-Debug-b7f65587d1f7aa43f2f9.json",
					"minimumCMakeVersion" : 
					{
						"string" : "3.8.0"
					},
					"parentIndex" : 1,
					"projectIndex" : 3,
					"source" : "interpreter/tests",
					"targetIndexes" : 
					[
						3,
						16
					]
				},
				{
					"build" : "interpreter/parser",
					"jsonFile" : "directory-interpreter.parser-Debug-707b160801921644bc26.json",
					"minimumCMakeVersion" : 
					{
						"string" : "3.21"
					},
					"parentIndex" : 1,
					"projectIndex" : 4,
					"source" : "interpreter/parser",
					"targetIndexes" : 
					[
						4,
						15
					]
				},
				{
					"build" : "text_transformer",
					"childIndexes" : 
					[
						6
					],
					"jsonFile" : "directory-text_transformer-Debug-99369a37fab41d57969e.json",
					"minimumCMakeVersion" : 
					{
						"string" : "3.21"
					},
					"parentIndex" : 0,
					"projectIndex" : 5,
					"source" : "text_transformer",
					"targetIndexes" : 
					[
						5,
						19
					]
				},
				{
					"build" : "_deps/json-build",
					"jsonFile" : "directory-_deps.json-build-Debug-b992325f012a7585f532.json",
					"minimumCMakeVersion" : 
					{
						"string" : "3.1"
					},
					"parentIndex" : 5,
					"projectIndex" : 6,
					"source" : "build/_deps/json-src",
					"targetIndexes" : 
					[
						6
					]
				},
				{
					"build" : "mmorpg_system_skill",
					"childIndexes" : 
					[
						8
					],
					"jsonFile" : "directory-mmorpg_system_skill-Debug-f9602b0679c0e9ff1069.json",
					"minimumCMakeVersion" : 
					{
						"string" : "3.21"
					},
					"parentIndex" : 0,
					"projectIndex" : 7,
					"source" : "mmorpg_system_skill",
					"targetIndexes" : 
					[
						7,
						17
					]
				},
				{
					"build" : "mmorpg_system_skill/tests",
					"jsonFile" : "directory-mmorpg_system_skill.tests-Debug-1e0f8ea7c93709b0747b.json",
					"minimumCMakeVersion" : 
					{
						"string" : "3.8.0"
					},
					"parentIndex" : 7,
					"projectIndex" : 8,
					"source" : "mmorpg_system_skill/tests",
					"targetIndexes" : 
					[
						8,
						18
					]
				},
				{
					"build" : "data_parse_logistic_company",
					"childIndexes" : 
					[
						10
					],
					"jsonFile" : "directory-data_parse_logistic_company-Debug-cab4e7fca3900bc69724.json",
					"minimumCMakeVersion" : 
					{
						"string" : "3.21"
					},
					"parentIndex" : 0,
					"projectIndex" : 9,
					"source" : "data_parse_logistic_company",
					"targetIndexes" : 
					[
						9,
						12
					]
				},
				{
					"build" : "data_parse_logistic_company/tests",
					"jsonFile" : "directory-data_parse_logistic_company.tests-Debug-80e30d731815d7b79319.json",
					"minimumCMakeVersion" : 
					{
						"string" : "3.8.0"
					},
					"parentIndex" : 9,
					"projectIndex" : 10,
					"source" : "data_parse_logistic_company/tests",
					"targetIndexes" : 
					[
						10,
						13
					]
				}
			],
			"name" : "Debug",
			"projects" : 
			[
				{
					"childIndexes" : 
					[
						1,
						5,
						7,
						9
					],
					"directoryIndexes" : 
					[
						0
					],
					"name" : "crcwrk",
					"targetIndexes" : 
					[
						0,
						11
					]
				},
				{
					"childIndexes" : 
					[
						2,
						3,
						4
					],
					"directoryIndexes" : 
					[
						1
					],
					"name" : "crcwrk_intprtr",
					"parentIndex" : 0,
					"targetIndexes" : 
					[
						1
					]
				},
				{
					"directoryIndexes" : 
					[
						2
					],
					"name" : "crcwrk_intprtr_lxr",
					"parentIndex" : 1,
					"targetIndexes" : 
					[
						2,
						14
					]
				},
				{
					"directoryIndexes" : 
					[
						3
					],
					"name" : "crcwrk_intprtr_tests",
					"parentIndex" : 1,
					"targetIndexes" : 
					[
						3,
						16
					]
				},
				{
					"directoryIndexes" : 
					[
						4
					],
					"name" : "crcwrk_intprtr_prsr",
					"parentIndex" : 1,
					"targetIndexes" : 
					[
						4,
						15
					]
				},
				{
					"childIndexes" : 
					[
						6
					],
					"directoryIndexes" : 
					[
						5
					],
					"name" : "crcwrk_txt_trans",
					"parentIndex" : 0,
					"targetIndexes" : 
					[
						5,
						19
					]
				},
				{
					"directoryIndexes" : 
					[
						6
					],
					"name" : "nlohmann_json",
					"parentIndex" : 5,
					"targetIndexes" : 
					[
						6
					]
				},
				{
					"childIndexes" : 
					[
						8
					],
					"directoryIndexes" : 
					[
						7
					],
					"name" : "crcwrk_mmorpg_sys_skll",
					"parentIndex" : 0,
					"targetIndexes" : 
					[
						7,
						17
					]
				},
				{
					"directoryIndexes" : 
					[
						8
					],
					"name" : "crcwrk_mmorpg_sys_skll_tests",
					"parentIndex" : 7,
					"targetIndexes" : 
					[
						8,
						18
					]
				},
				{
					"childIndexes" : 
					[
						10
					],
					"directoryIndexes" : 
					[
						9
					],
					"name" : "crcwrk_dt_prs_logic_company",
					"parentIndex" : 0,
					"targetIndexes" : 
					[
						9,
						12
					]
				},
				{
					"directoryIndexes" : 
					[
						10
					],
					"name" : "crcwrk_dt_prs_logic_company_tests",
					"parentIndex" : 9,
					"targetIndexes" : 
					[
						10,
						13
					]
				}
			],
			"targets" : 
			[
				{
					"directoryIndex" : 0,
					"id" : "ALL_BUILD::@6890427a1f51a3e7e1df",
					"jsonFile" : "target-ALL_BUILD-Debug-107aafeced8d68e44fab.json",
					"name" : "ALL_BUILD",
					"projectIndex" : 0
				},
				{
					"directoryIndex" : 1,
					"id" : "ALL_BUILD::@53be9898ecdd411495e6",
					"jsonFile" : "target-ALL_BUILD-Debug-cd44a5df5a1fd6ed46e4.json",
					"name" : "ALL_BUILD",
					"projectIndex" : 1
				},
				{
					"directoryIndex" : 2,
					"id" : "ALL_BUILD::@5a1904694c5a55962a68",
					"jsonFile" : "target-ALL_BUILD-Debug-a895e115feb985fe635c.json",
					"name" : "ALL_BUILD",
					"projectIndex" : 2
				},
				{
					"directoryIndex" : 3,
					"id" : "ALL_BUILD::@86ad6e73574f5b246b60",
					"jsonFile" : "target-ALL_BUILD-Debug-e440e49978aac2c8315e.json",
					"name" : "ALL_BUILD",
					"projectIndex" : 3
				},
				{
					"directoryIndex" : 4,
					"id" : "ALL_BUILD::@3a4963c009887eca9bf2",
					"jsonFile" : "target-ALL_BUILD-Debug-d807c780e91d5b27fefb.json",
					"name" : "ALL_BUILD",
					"projectIndex" : 4
				},
				{
					"directoryIndex" : 5,
					"id" : "ALL_BUILD::@477c085812b49bf1c903",
					"jsonFile" : "target-ALL_BUILD-Debug-13bcb8249f526af663b6.json",
					"name" : "ALL_BUILD",
					"projectIndex" : 5
				},
				{
					"directoryIndex" : 6,
					"id" : "ALL_BUILD::@1f73e43ed239fe3d59ae",
					"jsonFile" : "target-ALL_BUILD-Debug-e75019a8fdef92c01891.json",
					"name" : "ALL_BUILD",
					"projectIndex" : 6
				},
				{
					"directoryIndex" : 7,
					"id" : "ALL_BUILD::@e68b6759cec0008354ce",
					"jsonFile" : "target-ALL_BUILD-Debug-c3e0bbf4f309ab013e1c.json",
					"name" : "ALL_BUILD",
					"projectIndex" : 7
				},
				{
					"directoryIndex" : 8,
					"id" : "ALL_BUILD::@da7befd668b3fcaf5b68",
					"jsonFile" : "target-ALL_BUILD-Debug-abd781dfdb156a94af8c.json",
					"name" : "ALL_BUILD",
					"projectIndex" : 8
				},
				{
					"directoryIndex" : 9,
					"id" : "ALL_BUILD::@a0824e37ab92c3007e73",
					"jsonFile" : "target-ALL_BUILD-Debug-afb17767de0d06b9f0c5.json",
					"name" : "ALL_BUILD",
					"projectIndex" : 9
				},
				{
					"directoryIndex" : 10,
					"id" : "ALL_BUILD::@3f6bd541d6606c603115",
					"jsonFile" : "target-ALL_BUILD-Debug-0618af8ed5f234328771.json",
					"name" : "ALL_BUILD",
					"projectIndex" : 10
				},
				{
					"directoryIndex" : 0,
					"id" : "ZERO_CHECK::@6890427a1f51a3e7e1df",
					"jsonFile" : "target-ZERO_CHECK-Debug-a418c8eae3344d91db7f.json",
					"name" : "ZERO_CHECK",
					"projectIndex" : 0
				},
				{
					"directoryIndex" : 9,
					"id" : "crcwrk_dt_prs_logic_company::@a0824e37ab92c3007e73",
					"jsonFile" : "target-crcwrk_dt_prs_logic_company-Debug-8bfcf33b97627ef84a14.json",
					"name" : "crcwrk_dt_prs_logic_company",
					"projectIndex" : 9
				},
				{
					"directoryIndex" : 10,
					"id" : "crcwrk_dt_prs_logic_company_tests::@3f6bd541d6606c603115",
					"jsonFile" : "target-crcwrk_dt_prs_logic_company_tests-Debug-235f45105639c1862033.json",
					"name" : "crcwrk_dt_prs_logic_company_tests",
					"projectIndex" : 10
				},
				{
					"directoryIndex" : 2,
					"id" : "crcwrk_intprtr_lxr::@5a1904694c5a55962a68",
					"jsonFile" : "target-crcwrk_intprtr_lxr-Debug-8ee59a36b24cbddb96b8.json",
					"name" : "crcwrk_intprtr_lxr",
					"projectIndex" : 2
				},
				{
					"directoryIndex" : 4,
					"id" : "crcwrk_intprtr_prsr::@3a4963c009887eca9bf2",
					"jsonFile" : "target-crcwrk_intprtr_prsr-Debug-ae397826723c2149f1f9.json",
					"name" : "crcwrk_intprtr_prsr",
					"projectIndex" : 4
				},
				{
					"directoryIndex" : 3,
					"id" : "crcwrk_intprtr_tests::@86ad6e73574f5b246b60",
					"jsonFile" : "target-crcwrk_intprtr_tests-Debug-3260eb96c15a63150786.json",
					"name" : "crcwrk_intprtr_tests",
					"projectIndex" : 3
				},
				{
					"directoryIndex" : 7,
					"id" : "crcwrk_mmorpg_sys_skll::@e68b6759cec0008354ce",
					"jsonFile" : "target-crcwrk_mmorpg_sys_skll-Debug-402e9612dfeb3713c501.json",
					"name" : "crcwrk_mmorpg_sys_skll",
					"projectIndex" : 7
				},
				{
					"directoryIndex" : 8,
					"id" : "crcwrk_mmorpg_sys_skll_tests::@da7befd668b3fcaf5b68",
					"jsonFile" : "target-crcwrk_mmorpg_sys_skll_tests-Debug-5778c7a7c1292d787eeb.json",
					"name" : "crcwrk_mmorpg_sys_skll_tests",
					"projectIndex" : 8
				},
				{
					"directoryIndex" : 5,
					"id" : "crcwrk_txt_trans::@477c085812b49bf1c903",
					"jsonFile" : "target-crcwrk_txt_trans-Debug-17f363b4e57c947b084a.json",
					"name" : "crcwrk_txt_trans",
					"projectIndex" : 5
				}
			]
		},
		{
			"directories" : 
			[
				{
					"build" : ".",
					"childIndexes" : 
					[
						1,
						5,
						7,
						9
					],
					"jsonFile" : "directory-.-Release-d0094a50bb2071803777.json",
					"minimumCMakeVersion" : 
					{
						"string" : "3.21"
					},
					"projectIndex" : 0,
					"source" : ".",
					"targetIndexes" : 
					[
						0,
						11
					]
				},
				{
					"build" : "interpreter",
					"childIndexes" : 
					[
						2,
						3,
						4
					],
					"jsonFile" : "directory-interpreter-Release-ca7d5bde384c7024ebdc.json",
					"minimumCMakeVersion" : 
					{
						"string" : "3.21"
					},
					"parentIndex" : 0,
					"projectIndex" : 1,
					"source" : "interpreter",
					"targetIndexes" : 
					[
						1
					]
				},
				{
					"build" : "interpreter/lexer",
					"jsonFile" : "directory-interpreter.lexer-Release-67a70c55d324c48a79e6.json",
					"minimumCMakeVersion" : 
					{
						"string" : "3.21"
					},
					"parentIndex" : 1,
					"projectIndex" : 2,
					"source" : "interpreter/lexer",
					"targetIndexes" : 
					[
						2,
						14
					]
				},
				{
					"build" : "interpreter/tests",
					"jsonFile" : "directory-interpreter.tests-Release-b7f65587d1f7aa43f2f9.json",
					"minimumCMakeVersion" : 
					{
						"string" : "3.8.0"
					},
					"parentIndex" : 1,
					"projectIndex" : 3,
					"source" : "interpreter/tests",
					"targetIndexes" : 
					[
						3,
						16
					]
				},
				{
					"build" : "interpreter/parser",
					"jsonFile" : "directory-interpreter.parser-Release-707b160801921644bc26.json",
					"minimumCMakeVersion" : 
					{
						"string" : "3.21"
					},
					"parentIndex" : 1,
					"projectIndex" : 4,
					"source" : "interpreter/parser",
					"targetIndexes" : 
					[
						4,
						15
					]
				},
				{
					"build" : "text_transformer",
					"childIndexes" : 
					[
						6
					],
					"jsonFile" : "directory-text_transformer-Release-99369a37fab41d57969e.json",
					"minimumCMakeVersion" : 
					{
						"string" : "3.21"
					},
					"parentIndex" : 0,
					"projectIndex" : 5,
					"source" : "text_transformer",
					"targetIndexes" : 
					[
						5,
						19
					]
				},
				{
					"build" : "_deps/json-build",
					"jsonFile" : "directory-_deps.json-build-Release-b992325f012a7585f532.json",
					"minimumCMakeVersion" : 
					{
						"string" : "3.1"
					},
					"parentIndex" : 5,
					"projectIndex" : 6,
					"source" : "build/_deps/json-src",
					"targetIndexes" : 
					[
						6
					]
				},
				{
					"build" : "mmorpg_system_skill",
					"childIndexes" : 
					[
						8
					],
					"jsonFile" : "directory-mmorpg_system_skill-Release-f9602b0679c0e9ff1069.json",
					"minimumCMakeVersion" : 
					{
						"string" : "3.21"
					},
					"parentIndex" : 0,
					"projectIndex" : 7,
					"source" : "mmorpg_system_skill",
					"targetIndexes" : 
					[
						7,
						17
					]
				},
				{
					"build" : "mmorpg_system_skill/tests",
					"jsonFile" : "directory-mmorpg_system_skill.tests-Release-1e0f8ea7c93709b0747b.json",
					"minimumCMakeVersion" : 
					{
						"string" : "3.8.0"
					},
					"parentIndex" : 7,
					"projectIndex" : 8,
					"source" : "mmorpg_system_skill/tests",
					"targetIndexes" : 
					[
						8,
						18
					]
				},
				{
					"build" : "data_parse_logistic_company",
					"childIndexes" : 
					[
						10
					],
					"jsonFile" : "directory-data_parse_logistic_company-Release-cab4e7fca3900bc69724.json",
					"minimumCMakeVersion" : 
					{
						"string" : "3.21"
					},
					"parentIndex" : 0,
					"projectIndex" : 9,
					"source" : "data_parse_logistic_company",
					"targetIndexes" : 
					[
						9,
						12
					]
				},
				{
					"build" : "data_parse_logistic_company/tests",
					"jsonFile" : "directory-data_parse_logistic_company.tests-Release-80e30d731815d7b79319.json",
					"minimumCMakeVersion" : 
					{
						"string" : "3.8.0"
					},
					"parentIndex" : 9,
					"projectIndex" : 10,
					"source" : "data_parse_logistic_company/tests",
					"targetIndexes" : 
					[
						10,
						13
					]
				}
			],
			"name" : "Release",
			"projects" : 
			[
				{
					"childIndexes" : 
					[
						1,
						5,
						7,
						9
					],
					"directoryIndexes" : 
					[
						0
					],
					"name" : "crcwrk",
					"targetIndexes" : 
					[
						0,
						11
					]
				},
				{
					"childIndexes" : 
					[
						2,
						3,
						4
					],
					"directoryIndexes" : 
					[
						1
					],
					"name" : "crcwrk_intprtr",
					"parentIndex" : 0,
					"targetIndexes" : 
					[
						1
					]
				},
				{
					"directoryIndexes" : 
					[
						2
					],
					"name" : "crcwrk_intprtr_lxr",
					"parentIndex" : 1,
					"targetIndexes" : 
					[
						2,
						14
					]
				},
				{
					"directoryIndexes" : 
					[
						3
					],
					"name" : "crcwrk_intprtr_tests",
					"parentIndex" : 1,
					"targetIndexes" : 
					[
						3,
						16
					]
				},
				{
					"directoryIndexes" : 
					[
						4
					],
					"name" : "crcwrk_intprtr_prsr",
					"parentIndex" : 1,
					"targetIndexes" : 
					[
						4,
						15
					]
				},
				{
					"childIndexes" : 
					[
						6
					],
					"directoryIndexes" : 
					[
						5
					],
					"name" : "crcwrk_txt_trans",
					"parentIndex" : 0,
					"targetIndexes" : 
					[
						5,
						19
					]
				},
				{
					"directoryIndexes" : 
					[
						6
					],
					"name" : "nlohmann_json",
					"parentIndex" : 5,
					"targetIndexes" : 
					[
						6
					]
				},
				{
					"childIndexes" : 
					[
						8
					],
					"directoryIndexes" : 
					[
						7
					],
					"name" : "crcwrk_mmorpg_sys_skll",
					"parentIndex" : 0,
					"targetIndexes" : 
					[
						7,
						17
					]
				},
				{
					"directoryIndexes" : 
					[
						8
					],
					"name" : "crcwrk_mmorpg_sys_skll_tests",
					"parentIndex" : 7,
					"targetIndexes" : 
					[
						8,
						18
					]
				},
				{
					"childIndexes" : 
					[
						10
					],
					"directoryIndexes" : 
					[
						9
					],
					"name" : "crcwrk_dt_prs_logic_company",
					"parentIndex" : 0,
					"targetIndexes" : 
					[
						9,
						12
					]
				},
				{
					"directoryIndexes" : 
					[
						10
					],
					"name" : "crcwrk_dt_prs_logic_company_tests",
					"parentIndex" : 9,
					"targetIndexes" : 
					[
						10,
						13
					]
				}
			],
			"targets" : 
			[
				{
					"directoryIndex" : 0,
					"id" : "ALL_BUILD::@6890427a1f51a3e7e1df",
					"jsonFile" : "target-ALL_BUILD-Release-107aafeced8d68e44fab.json",
					"name" : "ALL_BUILD",
					"projectIndex" : 0
				},
				{
					"directoryIndex" : 1,
					"id" : "ALL_BUILD::@53be9898ecdd411495e6",
					"jsonFile" : "target-ALL_BUILD-Release-cd44a5df5a1fd6ed46e4.json",
					"name" : "ALL_BUILD",
					"projectIndex" : 1
				},
				{
					"directoryIndex" : 2,
					"id" : "ALL_BUILD::@5a1904694c5a55962a68",
					"jsonFile" : "target-ALL_BUILD-Release-a895e115feb985fe635c.json",
					"name" : "ALL_BUILD",
					"projectIndex" : 2
				},
				{
					"directoryIndex" : 3,
					"id" : "ALL_BUILD::@86ad6e73574f5b246b60",
					"jsonFile" : "target-ALL_BUILD-Release-e440e49978aac2c8315e.json",
					"name" : "ALL_BUILD",
					"projectIndex" : 3
				},
				{
					"directoryIndex" : 4,
					"id" : "ALL_BUILD::@3a4963c009887eca9bf2",
					"jsonFile" : "target-ALL_BUILD-Release-d807c780e91d5b27fefb.json",
					"name" : "ALL_BUILD",
					"projectIndex" : 4
				},
				{
					"directoryIndex" : 5,
					"id" : "ALL_BUILD::@477c085812b49bf1c903",
					"jsonFile" : "target-ALL_BUILD-Release-13bcb8249f526af663b6.json",
					"name" : "ALL_BUILD",
					"projectIndex" : 5
				},
				{
					"directoryIndex" : 6,
					"id" : "ALL_BUILD::@1f73e43ed239fe3d59ae",
					"jsonFile" : "target-ALL_BUILD-Release-e75019a8fdef92c01891.json",
					"name" : "ALL_BUILD",
					"projectIndex" : 6
				},
				{
					"directoryIndex" : 7,
					"id" : "ALL_BUILD::@e68b6759cec0008354ce",
					"jsonFile" : "target-ALL_BUILD-Release-c3e0bbf4f309ab013e1c.json",
					"name" : "ALL_BUILD",
					"projectIndex" : 7
				},
				{
					"directoryIndex" : 8,
					"id" : "ALL_BUILD::@da7befd668b3fcaf5b68",
					"jsonFile" : "target-ALL_BUILD-Release-abd781dfdb156a94af8c.json",
					"name" : "ALL_BUILD",
					"projectIndex" : 8
				},
				{
					"directoryIndex" : 9,
					"id" : "ALL_BUILD::@a0824e37ab92c3007e73",
					"jsonFile" : "target-ALL_BUILD-Release-afb17767de0d06b9f0c5.json",
					"name" : "ALL_BUILD",
					"projectIndex" : 9
				},
				{
					"directoryIndex" : 10,
					"id" : "ALL_BUILD::@3f6bd541d6606c603115",
					"jsonFile" : "target-ALL_BUILD-Release-0618af8ed5f234328771.json",
					"name" : "ALL_BUILD",
					"projectIndex" : 10
				},
				{
					"directoryIndex" : 0,
					"id" : "ZERO_CHECK::@6890427a1f51a3e7e1df",
					"jsonFile" : "target-ZERO_CHECK-Release-a418c8eae3344d91db7f.json",
					"name" : "ZERO_CHECK",
					"projectIndex" : 0
				},
				{
					"directoryIndex" : 9,
					"id" : "crcwrk_dt_prs_logic_company::@a0824e37ab92c3007e73",
					"jsonFile" : "target-crcwrk_dt_prs_logic_company-Release-980f54316bfc77d3f49f.json",
					"name" : "crcwrk_dt_prs_logic_company",
					"projectIndex" : 9
				},
				{
					"directoryIndex" : 10,
					"id" : "crcwrk_dt_prs_logic_company_tests::@3f6bd541d6606c603115",
					"jsonFile" : "target-crcwrk_dt_prs_logic_company_tests-Release-1232456c25e0e775566a.json",
					"name" : "crcwrk_dt_prs_logic_company_tests",
					"projectIndex" : 10
				},
				{
					"directoryIndex" : 2,
					"id" : "crcwrk_intprtr_lxr::@5a1904694c5a55962a68",
					"jsonFile" : "target-crcwrk_intprtr_lxr-Release-a2aa7b831da8df166e65.json",
					"name" : "crcwrk_intprtr_lxr",
					"projectIndex" : 2
				},
				{
					"directoryIndex" : 4,
					"id" : "crcwrk_intprtr_prsr::@3a4963c009887eca9bf2",
					"jsonFile" : "target-crcwrk_intprtr_prsr-Release-595acd24e5b822b74de6.json",
					"name" : "crcwrk_intprtr_prsr",
					"projectIndex" : 4
				},
				{
					"directoryIndex" : 3,
					"id" : "crcwrk_intprtr_tests::@86ad6e73574f5b246b60",
					"jsonFile" : "target-crcwrk_intprtr_tests-Release-4f799a10155c787bf740.json",
					"name" : "crcwrk_intprtr_tests",
					"projectIndex" : 3
				},
				{
					"directoryIndex" : 7,
					"id" : "crcwrk_mmorpg_sys_skll::@e68b6759cec0008354ce",
					"jsonFile" : "target-crcwrk_mmorpg_sys_skll-Release-fac983be7295669cfb77.json",
					"name" : "crcwrk_mmorpg_sys_skll",
					"projectIndex" : 7
				},
				{
					"directoryIndex" : 8,
					"id" : "crcwrk_mmorpg_sys_skll_tests::@da7befd668b3fcaf5b68",
					"jsonFile" : "target-crcwrk_mmorpg_sys_skll_tests-Release-ff2199c44c4854ce8518.json",
					"name" : "crcwrk_mmorpg_sys_skll_tests",
					"projectIndex" : 8
				},
				{
					"directoryIndex" : 5,
					"id" : "crcwrk_txt_trans::@477c085812b49bf1c903",
					"jsonFile" : "target-crcwrk_txt_trans-Release-7973df61b9ec95fb5c91.json",
					"name" : "crcwrk_txt_trans",
					"projectIndex" : 5
				}
			]
		},
		{
			"directories" : 
			[
				{
					"build" : ".",
					"childIndexes" : 
					[
						1,
						5,
						7,
						9
					],
					"jsonFile" : "directory-.-MinSizeRel-d0094a50bb2071803777.json",
					"minimumCMakeVersion" : 
					{
						"string" : "3.21"
					},
					"projectIndex" : 0,
					"source" : ".",
					"targetIndexes" : 
					[
						0,
						11
					]
				},
				{
					"build" : "interpreter",
					"childIndexes" : 
					[
						2,
						3,
						4
					],
					"jsonFile" : "directory-interpreter-MinSizeRel-ca7d5bde384c7024ebdc.json",
					"minimumCMakeVersion" : 
					{
						"string" : "3.21"
					},
					"parentIndex" : 0,
					"projectIndex" : 1,
					"source" : "interpreter",
					"targetIndexes" : 
					[
						1
					]
				},
				{
					"build" : "interpreter/lexer",
					"jsonFile" : "directory-interpreter.lexer-MinSizeRel-67a70c55d324c48a79e6.json",
					"minimumCMakeVersion" : 
					{
						"string" : "3.21"
					},
					"parentIndex" : 1,
					"projectIndex" : 2,
					"source" : "interpreter/lexer",
					"targetIndexes" : 
					[
						2,
						14
					]
				},
				{
					"build" : "interpreter/tests",
					"jsonFile" : "directory-interpreter.tests-MinSizeRel-b7f65587d1f7aa43f2f9.json",
					"minimumCMakeVersion" : 
					{
						"string" : "3.8.0"
					},
					"parentIndex" : 1,
					"projectIndex" : 3,
					"source" : "interpreter/tests",
					"targetIndexes" : 
					[
						3,
						16
					]
				},
				{
					"build" : "interpreter/parser",
					"jsonFile" : "directory-interpreter.parser-MinSizeRel-707b160801921644bc26.json",
					"minimumCMakeVersion" : 
					{
						"string" : "3.21"
					},
					"parentIndex" : 1,
					"projectIndex" : 4,
					"source" : "interpreter/parser",
					"targetIndexes" : 
					[
						4,
						15
					]
				},
				{
					"build" : "text_transformer",
					"childIndexes" : 
					[
						6
					],
					"jsonFile" : "directory-text_transformer-MinSizeRel-99369a37fab41d57969e.json",
					"minimumCMakeVersion" : 
					{
						"string" : "3.21"
					},
					"parentIndex" : 0,
					"projectIndex" : 5,
					"source" : "text_transformer",
					"targetIndexes" : 
					[
						5,
						19
					]
				},
				{
					"build" : "_deps/json-build",
					"jsonFile" : "directory-_deps.json-build-MinSizeRel-b992325f012a7585f532.json",
					"minimumCMakeVersion" : 
					{
						"string" : "3.1"
					},
					"parentIndex" : 5,
					"projectIndex" : 6,
					"source" : "build/_deps/json-src",
					"targetIndexes" : 
					[
						6
					]
				},
				{
					"build" : "mmorpg_system_skill",
					"childIndexes" : 
					[
						8
					],
					"jsonFile" : "directory-mmorpg_system_skill-MinSizeRel-f9602b0679c0e9ff1069.json",
					"minimumCMakeVersion" : 
					{
						"string" : "3.21"
					},
					"parentIndex" : 0,
					"projectIndex" : 7,
					"source" : "mmorpg_system_skill",
					"targetIndexes" : 
					[
						7,
						17
					]
				},
				{
					"build" : "mmorpg_system_skill/tests",
					"jsonFile" : "directory-mmorpg_system_skill.tests-MinSizeRel-1e0f8ea7c93709b0747b.json",
					"minimumCMakeVersion" : 
					{
						"string" : "3.8.0"
					},
					"parentIndex" : 7,
					"projectIndex" : 8,
					"source" : "mmorpg_system_skill/tests",
					"targetIndexes" : 
					[
						8,
						18
					]
				},
				{
					"build" : "data_parse_logistic_company",
					"childIndexes" : 
					[
						10
					],
					"jsonFile" : "directory-data_parse_logistic_company-MinSizeRel-cab4e7fca3900bc69724.json",
					"minimumCMakeVersion" : 
					{
						"string" : "3.21"
					},
					"parentIndex" : 0,
					"projectIndex" : 9,
					"source" : "data_parse_logistic_company",
					"targetIndexes" : 
					[
						9,
						12
					]
				},
				{
					"build" : "data_parse_logistic_company/tests",
					"jsonFile" : "directory-data_parse_logistic_company.tests-MinSizeRel-80e30d731815d7b79319.json",
					"minimumCMakeVersion" : 
					{
						"string" : "3.8.0"
					},
					"parentIndex" : 9,
					"projectIndex" : 10,
					"source" : "data_parse_logistic_company/tests",
					"targetIndexes" : 
					[
						10,
						13
					]
				}
			],
			"name" : "MinSizeRel",
			"projects" : 
			[
				{
					"childIndexes" : 
					[
						1,
						5,
						7,
						9
					],
					"directoryIndexes" : 
					[
						0
					],
					"name" : "crcwrk",
					"targetIndexes" : 
					[
						0,
						11
					]
				},
				{
					"childIndexes" : 
					[
						2,
						3,
						4
					],
					"directoryIndexes" : 
					[
						1
					],
					"name" : "crcwrk_intprtr",
					"parentIndex" : 0,
					"targetIndexes" : 
					[
						1
					]
				},
				{
					"directoryIndexes" : 
					[
						2
					],
					"name" : "crcwrk_intprtr_lxr",
					"parentIndex" : 1,
					"targetIndexes" : 
					[
						2,
						14
					]
				},
				{
					"directoryIndexes" : 
					[
						3
					],
					"name" : "crcwrk_intprtr_tests",
					"parentIndex" : 1,
					"targetIndexes" : 
					[
						3,
						16
					]
				},
				{
					"directoryIndexes" : 
					[
						4
					],
					"name" : "crcwrk_intprtr_prsr",
					"parentIndex" : 1,
					"targetIndexes" : 
					[
						4,
						15
					]
				},
				{
					"childIndexes" : 
					[
						6
					],
					"directoryIndexes" : 
					[
						5
					],
					"name" : "crcwrk_txt_trans",
					"parentIndex" : 0,
					"targetIndexes" : 
					[
						5,
						19
					]
				},
				{
					"directoryIndexes" : 
					[
						6
					],
					"name" : "nlohmann_json",
					"parentIndex" : 5,
					"targetIndexes" : 
					[
						6
					]
				},
				{
					"childIndexes" : 
					[
						8
					],
					"directoryIndexes" : 
					[
						7
					],
					"name" : "crcwrk_mmorpg_sys_skll",
					"parentIndex" : 0,
					"targetIndexes" : 
					[
						7,
						17
					]
				},
				{
					"directoryIndexes" : 
					[
						8
					],
					"name" : "crcwrk_mmorpg_sys_skll_tests",
					"parentIndex" : 7,
					"targetIndexes" : 
					[
						8,
						18
					]
				},
				{
					"childIndexes" : 
					[
						10
					],
					"directoryIndexes" : 
					[
						9
					],
					"name" : "crcwrk_dt_prs_logic_company",
					"parentIndex" : 0,
					"targetIndexes" : 
					[
						9,
						12
					]
				},
				{
					"directoryIndexes" : 
					[
						10
					],
					"name" : "crcwrk_dt_prs_logic_company_tests",
					"parentIndex" : 9,
					"targetIndexes" : 
					[
						10,
						13
					]
				}
			],
			"targets" : 
			[
				{
					"directoryIndex" : 0,
					"id" : "ALL_BUILD::@6890427a1f51a3e7e1df",
					"jsonFile" : "target-ALL_BUILD-MinSizeRel-107aafeced8d68e44fab.json",
					"name" : "ALL_BUILD",
					"projectIndex" : 0
				},
				{
					"directoryIndex" : 1,
					"id" : "ALL_BUILD::@53be9898ecdd411495e6",
					"jsonFile" : "target-ALL_BUILD-MinSizeRel-cd44a5df5a1fd6ed46e4.json",
					"name" : "ALL_BUILD",
					"projectIndex" : 1
				},
				{
					"directoryIndex" : 2,
					"id" : "ALL_BUILD::@5a1904694c5a55962a68",
					"jsonFile" : "target-ALL_BUILD-MinSizeRel-a895e115feb985fe635c.json",
					"name" : "ALL_BUILD",
					"projectIndex" : 2
				},
				{
					"directoryIndex" : 3,
					"id" : "ALL_BUILD::@86ad6e73574f5b246b60",
					"jsonFile" : "target-ALL_BUILD-MinSizeRel-e440e49978aac2c8315e.json",
					"name" : "ALL_BUILD",
					"projectIndex" : 3
				},
				{
					"directoryIndex" : 4,
					"id" : "ALL_BUILD::@3a4963c009887eca9bf2",
					"jsonFile" : "target-ALL_BUILD-MinSizeRel-d807c780e91d5b27fefb.json",
					"name" : "ALL_BUILD",
					"projectIndex" : 4
				},
				{
					"directoryIndex" : 5,
					"id" : "ALL_BUILD::@477c085812b49bf1c903",
					"jsonFile" : "target-ALL_BUILD-MinSizeRel-13bcb8249f526af663b6.json",
					"name" : "ALL_BUILD",
					"projectIndex" : 5
				},
				{
					"directoryIndex" : 6,
					"id" : "ALL_BUILD::@1f73e43ed239fe3d59ae",
					"jsonFile" : "target-ALL_BUILD-MinSizeRel-e75019a8fdef92c01891.json",
					"name" : "ALL_BUILD",
					"projectIndex" : 6
				},
				{
					"directoryIndex" : 7,
					"id" : "ALL_BUILD::@e68b6759cec0008354ce",
					"jsonFile" : "target-ALL_BUILD-MinSizeRel-c3e0bbf4f309ab013e1c.json",
					"name" : "ALL_BUILD",
					"projectIndex" : 7
				},
				{
					"directoryIndex" : 8,
					"id" : "ALL_BUILD::@da7befd668b3fcaf5b68",
					"jsonFile" : "target-ALL_BUILD-MinSizeRel-abd781dfdb156a94af8c.json",
					"name" : "ALL_BUILD",
					"projectIndex" : 8
				},
				{
					"directoryIndex" : 9,
					"id" : "ALL_BUILD::@a0824e37ab92c3007e73",
					"jsonFile" : "target-ALL_BUILD-MinSizeRel-afb17767de0d06b9f0c5.json",
					"name" : "ALL_BUILD",
					"projectIndex" : 9
				},
				{
					"directoryIndex" : 10,
					"id" : "ALL_BUILD::@3f6bd541d6606c603115",
					"jsonFile" : "target-ALL_BUILD-MinSizeRel-0618af8ed5f234328771.json",
					"name" : "ALL_BUILD",
					"projectIndex" : 10
				},
				{
					"directoryIndex" : 0,
					"id" : "ZERO_CHECK::@6890427a1f51a3e7e1df",
					"jsonFile" : "target-ZERO_CHECK-MinSizeRel-a418c8eae3344d91db7f.json",
					"name" : "ZERO_CHECK",
					"projectIndex" : 0
				},
				{
					"directoryIndex" : 9,
					"id" : "crcwrk_dt_prs_logic_company::@a0824e37ab92c3007e73",
					"jsonFile" : "target-crcwrk_dt_prs_logic_company-MinSizeRel-ca74a7449b303f7262ff.json",
					"name" : "crcwrk_dt_prs_logic_company",
					"projectIndex" : 9
				},
				{
					"directoryIndex" : 10,
					"id" : "crcwrk_dt_prs_logic_company_tests::@3f6bd541d6606c603115",
					"jsonFile" : "target-crcwrk_dt_prs_logic_company_tests-MinSizeRel-6acc75c57e15441fab2b.json",
					"name" : "crcwrk_dt_prs_logic_company_tests",
					"projectIndex" : 10
				},
				{
					"directoryIndex" : 2,
					"id" : "crcwrk_intprtr_lxr::@5a1904694c5a55962a68",
					"jsonFile" : "target-crcwrk_intprtr_lxr-MinSizeRel-a55a229d32054990fa84.json",
					"name" : "crcwrk_intprtr_lxr",
					"projectIndex" : 2
				},
				{
					"directoryIndex" : 4,
					"id" : "crcwrk_intprtr_prsr::@3a4963c009887eca9bf2",
					"jsonFile" : "target-crcwrk_intprtr_prsr-MinSizeRel-cdd2af98b37315bc9ae0.json",
					"name" : "crcwrk_intprtr_prsr",
					"projectIndex" : 4
				},
				{
					"directoryIndex" : 3,
					"id" : "crcwrk_intprtr_tests::@86ad6e73574f5b246b60",
					"jsonFile" : "target-crcwrk_intprtr_tests-MinSizeRel-b2403df123570077d6c4.json",
					"name" : "crcwrk_intprtr_tests",
					"projectIndex" : 3
				},
				{
					"directoryIndex" : 7,
					"id" : "crcwrk_mmorpg_sys_skll::@e68b6759cec0008354ce",
					"jsonFile" : "target-crcwrk_mmorpg_sys_skll-MinSizeRel-4dcde1703ee70180fe7c.json",
					"name" : "crcwrk_mmorpg_sys_skll",
					"projectIndex" : 7
				},
				{
					"directoryIndex" : 8,
					"id" : "crcwrk_mmorpg_sys_skll_tests::@da7befd668b3fcaf5b68",
					"jsonFile" : "target-crcwrk_mmorpg_sys_skll_tests-MinSizeRel-ff4a629ac9546072020b.json",
					"name" : "crcwrk_mmorpg_sys_skll_tests",
					"projectIndex" : 8
				},
				{
					"directoryIndex" : 5,
					"id" : "crcwrk_txt_trans::@477c085812b49bf1c903",
					"jsonFile" : "target-crcwrk_txt_trans-MinSizeRel-fbb87d8596ace2b16f27.json",
					"name" : "crcwrk_txt_trans",
					"projectIndex" : 5
				}
			]
		},
		{
			"directories" : 
			[
				{
					"build" : ".",
					"childIndexes" : 
					[
						1,
						5,
						7,
						9
					],
					"jsonFile" : "directory-.-RelWithDebInfo-d0094a50bb2071803777.json",
					"minimumCMakeVersion" : 
					{
						"string" : "3.21"
					},
					"projectIndex" : 0,
					"source" : ".",
					"targetIndexes" : 
					[
						0,
						11
					]
				},
				{
					"build" : "interpreter",
					"childIndexes" : 
					[
						2,
						3,
						4
					],
					"jsonFile" : "directory-interpreter-RelWithDebInfo-ca7d5bde384c7024ebdc.json",
					"minimumCMakeVersion" : 
					{
						"string" : "3.21"
					},
					"parentIndex" : 0,
					"projectIndex" : 1,
					"source" : "interpreter",
					"targetIndexes" : 
					[
						1
					]
				},
				{
					"build" : "interpreter/lexer",
					"jsonFile" : "directory-interpreter.lexer-RelWithDebInfo-67a70c55d324c48a79e6.json",
					"minimumCMakeVersion" : 
					{
						"string" : "3.21"
					},
					"parentIndex" : 1,
					"projectIndex" : 2,
					"source" : "interpreter/lexer",
					"targetIndexes" : 
					[
						2,
						14
					]
				},
				{
					"build" : "interpreter/tests",
					"jsonFile" : "directory-interpreter.tests-RelWithDebInfo-b7f65587d1f7aa43f2f9.json",
					"minimumCMakeVersion" : 
					{
						"string" : "3.8.0"
					},
					"parentIndex" : 1,
					"projectIndex" : 3,
					"source" : "interpreter/tests",
					"targetIndexes" : 
					[
						3,
						16
					]
				},
				{
					"build" : "interpreter/parser",
					"jsonFile" : "directory-interpreter.parser-RelWithDebInfo-707b160801921644bc26.json",
					"minimumCMakeVersion" : 
					{
						"string" : "3.21"
					},
					"parentIndex" : 1,
					"projectIndex" : 4,
					"source" : "interpreter/parser",
					"targetIndexes" : 
					[
						4,
						15
					]
				},
				{
					"build" : "text_transformer",
					"childIndexes" : 
					[
						6
					],
					"jsonFile" : "directory-text_transformer-RelWithDebInfo-99369a37fab41d57969e.json",
					"minimumCMakeVersion" : 
					{
						"string" : "3.21"
					},
					"parentIndex" : 0,
					"projectIndex" : 5,
					"source" : "text_transformer",
					"targetIndexes" : 
					[
						5,
						19
					]
				},
				{
					"build" : "_deps/json-build",
					"jsonFile" : "directory-_deps.json-build-RelWithDebInfo-b992325f012a7585f532.json",
					"minimumCMakeVersion" : 
					{
						"string" : "3.1"
					},
					"parentIndex" : 5,
					"projectIndex" : 6,
					"source" : "build/_deps/json-src",
					"targetIndexes" : 
					[
						6
					]
				},
				{
					"build" : "mmorpg_system_skill",
					"childIndexes" : 
					[
						8
					],
					"jsonFile" : "directory-mmorpg_system_skill-RelWithDebInfo-f9602b0679c0e9ff1069.json",
					"minimumCMakeVersion" : 
					{
						"string" : "3.21"
					},
					"parentIndex" : 0,
					"projectIndex" : 7,
					"source" : "mmorpg_system_skill",
					"targetIndexes" : 
					[
						7,
						17
					]
				},
				{
					"build" : "mmorpg_system_skill/tests",
					"jsonFile" : "directory-mmorpg_system_skill.tests-RelWithDebInfo-1e0f8ea7c93709b0747b.json",
					"minimumCMakeVersion" : 
					{
						"string" : "3.8.0"
					},
					"parentIndex" : 7,
					"projectIndex" : 8,
					"source" : "mmorpg_system_skill/tests",
					"targetIndexes" : 
					[
						8,
						18
					]
				},
				{
					"build" : "data_parse_logistic_company",
					"childIndexes" : 
					[
						10
					],
					"jsonFile" : "directory-data_parse_logistic_company-RelWithDebInfo-cab4e7fca3900bc69724.json",
					"minimumCMakeVersion" : 
					{
						"string" : "3.21"
					},
					"parentIndex" : 0,
					"projectIndex" : 9,
					"source" : "data_parse_logistic_company",
					"targetIndexes" : 
					[
						9,
						12
					]
				},
				{
					"build" : "data_parse_logistic_company/tests",
					"jsonFile" : "directory-data_parse_logistic_company.tests-RelWithDebInfo-80e30d731815d7b79319.json",
					"minimumCMakeVersion" : 
					{
						"string" : "3.8.0"
					},
					"parentIndex" : 9,
					"projectIndex" : 10,
					"source" : "data_parse_logistic_company/tests",
					"targetIndexes" : 
					[
						10,
						13
					]
				}
			],
			"name" : "RelWithDebInfo",
			"projects" : 
			[
				{
					"childIndexes" : 
					[
						1,
						5,
						7,
						9
					],
					"directoryIndexes" : 
					[
						0
					],
					"name" : "crcwrk",
					"targetIndexes" : 
					[
						0,
						11
					]
				},
				{
					"childIndexes" : 
					[
						2,
						3,
						4
					],
					"directoryIndexes" : 
					[
						1
					],
					"name" : "crcwrk_intprtr",
					"parentIndex" : 0,
					"targetIndexes" : 
					[
						1
					]
				},
				{
					"directoryIndexes" : 
					[
						2
					],
					"name" : "crcwrk_intprtr_lxr",
					"parentIndex" : 1,
					"targetIndexes" : 
					[
						2,
						14
					]
				},
				{
					"directoryIndexes" : 
					[
						3
					],
					"name" : "crcwrk_intprtr_tests",
					"parentIndex" : 1,
					"targetIndexes" : 
					[
						3,
						16
					]
				},
				{
					"directoryIndexes" : 
					[
						4
					],
					"name" : "crcwrk_intprtr_prsr",
					"parentIndex" : 1,
					"targetIndexes" : 
					[
						4,
						15
					]
				},
				{
					"childIndexes" : 
					[
						6
					],
					"directoryIndexes" : 
					[
						5
					],
					"name" : "crcwrk_txt_trans",
					"parentIndex" : 0,
					"targetIndexes" : 
					[
						5,
						19
					]
				},
				{
					"directoryIndexes" : 
					[
						6
					],
					"name" : "nlohmann_json",
					"parentIndex" : 5,
					"targetIndexes" : 
					[
						6
					]
				},
				{
					"childIndexes" : 
					[
						8
					],
					"directoryIndexes" : 
					[
						7
					],
					"name" : "crcwrk_mmorpg_sys_skll",
					"parentIndex" : 0,
					"targetIndexes" : 
					[
						7,
						17
					]
				},
				{
					"directoryIndexes" : 
					[
						8
					],
					"name" : "crcwrk_mmorpg_sys_skll_tests",
					"parentIndex" : 7,
					"targetIndexes" : 
					[
						8,
						18
					]
				},
				{
					"childIndexes" : 
					[
						10
					],
					"directoryIndexes" : 
					[
						9
					],
					"name" : "crcwrk_dt_prs_logic_company",
					"parentIndex" : 0,
					"targetIndexes" : 
					[
						9,
						12
					]
				},
				{
					"directoryIndexes" : 
					[
						10
					],
					"name" : "crcwrk_dt_prs_logic_company_tests",
					"parentIndex" : 9,
					"targetIndexes" : 
					[
						10,
						13
					]
				}
			],
			"targets" : 
			[
				{
					"directoryIndex" : 0,
					"id" : "ALL_BUILD::@6890427a1f51a3e7e1df",
					"jsonFile" : "target-ALL_BUILD-RelWithDebInfo-107aafeced8d68e44fab.json",
					"name" : "ALL_BUILD",
					"projectIndex" : 0
				},
				{
					"directoryIndex" : 1,
					"id" : "ALL_BUILD::@53be9898ecdd411495e6",
					"jsonFile" : "target-ALL_BUILD-RelWithDebInfo-cd44a5df5a1fd6ed46e4.json",
					"name" : "ALL_BUILD",
					"projectIndex" : 1
				},
				{
					"directoryIndex" : 2,
					"id" : "ALL_BUILD::@5a1904694c5a55962a68",
					"jsonFile" : "target-ALL_BUILD-RelWithDebInfo-a895e115feb985fe635c.json",
					"name" : "ALL_BUILD",
					"projectIndex" : 2
				},
				{
					"directoryIndex" : 3,
					"id" : "ALL_BUILD::@86ad6e73574f5b246b60",
					"jsonFile" : "target-ALL_BUILD-RelWithDebInfo-e440e49978aac2c8315e.json",
					"name" : "ALL_BUILD",
					"projectIndex" : 3
				},
				{
					"directoryIndex" : 4,
					"id" : "ALL_BUILD::@3a4963c009887eca9bf2",
					"jsonFile" : "target-ALL_BUILD-RelWithDebInfo-d807c780e91d5b27fefb.json",
					"name" : "ALL_BUILD",
					"projectIndex" : 4
				},
				{
					"directoryIndex" : 5,
					"id" : "ALL_BUILD::@477c085812b49bf1c903",
					"jsonFile" : "target-ALL_BUILD-RelWithDebInfo-13bcb8249f526af663b6.json",
					"name" : "ALL_BUILD",
					"projectIndex" : 5
				},
				{
					"directoryIndex" : 6,
					"id" : "ALL_BUILD::@1f73e43ed239fe3d59ae",
					"jsonFile" : "target-ALL_BUILD-RelWithDebInfo-e75019a8fdef92c01891.json",
					"name" : "ALL_BUILD",
					"projectIndex" : 6
				},
				{
					"directoryIndex" : 7,
					"id" : "ALL_BUILD::@e68b6759cec0008354ce",
					"jsonFile" : "target-ALL_BUILD-RelWithDebInfo-c3e0bbf4f309ab013e1c.json",
					"name" : "ALL_BUILD",
					"projectIndex" : 7
				},
				{
					"directoryIndex" : 8,
					"id" : "ALL_BUILD::@da7befd668b3fcaf5b68",
					"jsonFile" : "target-ALL_BUILD-RelWithDebInfo-abd781dfdb156a94af8c.json",
					"name" : "ALL_BUILD",
					"projectIndex" : 8
				},
				{
					"directoryIndex" : 9,
					"id" : "ALL_BUILD::@a0824e37ab92c3007e73",
					"jsonFile" : "target-ALL_BUILD-RelWithDebInfo-afb17767de0d06b9f0c5.json",
					"name" : "ALL_BUILD",
					"projectIndex" : 9
				},
				{
					"directoryIndex" : 10,
					"id" : "ALL_BUILD::@3f6bd541d6606c603115",
					"jsonFile" : "target-ALL_BUILD-RelWithDebInfo-0618af8ed5f234328771.json",
					"name" : "ALL_BUILD",
					"projectIndex" : 10
				},
				{
					"directoryIndex" : 0,
					"id" : "ZERO_CHECK::@6890427a1f51a3e7e1df",
					"jsonFile" : "target-ZERO_CHECK-RelWithDebInfo-a418c8eae3344d91db7f.json",
					"name" : "ZERO_CHECK",
					"projectIndex" : 0
				},
				{
					"directoryIndex" : 9,
					"id" : "crcwrk_dt_prs_logic_company::@a0824e37ab92c3007e73",
					"jsonFile" : "target-crcwrk_dt_prs_logic_company-RelWithDebInfo-3146c78003bfffc99aaa.json",
					"name" : "crcwrk_dt_prs_logic_company",
					"projectIndex" : 9
				},
				{
					"directoryIndex" : 10,
					"id" : "crcwrk_dt_prs_logic_company_tests::@3f6bd541d6606c603115",
					"jsonFile" : "target-crcwrk_dt_prs_logic_company_tests-RelWithDebInfo-d1a1bf09d92bed1b6924.json",
					"name" : "crcwrk_dt_prs_logic_company_tests",
					"projectIndex" : 10
				},
				{
					"directoryIndex" : 2,
					"id" : "crcwrk_intprtr_lxr::@5a1904694c5a55962a68",
					"jsonFile" : "target-crcwrk_intprtr_lxr-RelWithDebInfo-cd9dbbb73aae1f96dc39.json",
					"name" : "crcwrk_intprtr_lxr",
					"projectIndex" : 2
				},
				{
					"directoryIndex" : 4,
					"id" : "crcwrk_intprtr_prsr::@3a4963c009887eca9bf2",
					"jsonFile" : "target-crcwrk_intprtr_prsr-RelWithDebInfo-1a439cfcb847f5d22c81.json",
					"name" : "crcwrk_intprtr_prsr",
					"projectIndex" : 4
				},
				{
					"directoryIndex" : 3,
					"id" : "crcwrk_intprtr_tests::@86ad6e73574f5b246b60",
					"jsonFile" : "target-crcwrk_intprtr_tests-RelWithDebInfo-4e349553adeb305a00fc.json",
					"name" : "crcwrk_intprtr_tests",
					"projectIndex" : 3
				},
				{
					"directoryIndex" : 7,
					"id" : "crcwrk_mmorpg_sys_skll::@e68b6759cec0008354ce",
					"jsonFile" : "target-crcwrk_mmorpg_sys_skll-RelWithDebInfo-576917c097aceceb775c.json",
					"name" : "crcwrk_mmorpg_sys_skll",
					"projectIndex" : 7
				},
				{
					"directoryIndex" : 8,
					"id" : "crcwrk_mmorpg_sys_skll_tests::@da7befd668b3fcaf5b68",
					"jsonFile" : "target-crcwrk_mmorpg_sys_skll_tests-RelWithDebInfo-b4cf3a5f3ae565514ce7.json",
					"name" : "crcwrk_mmorpg_sys_skll_tests",
					"projectIndex" : 8
				},
				{
					"directoryIndex" : 5,
					"id" : "crcwrk_txt_trans::@477c085812b49bf1c903",
					"jsonFile" : "target-crcwrk_txt_trans-RelWithDebInfo-2dd7b841d81ab4f9568a.json",
					"name" : "crcwrk_txt_trans",
					"projectIndex" : 5
				}
			]
		}
	],
	"kind" : "codemodel",
	"paths" : 
	{
		"build" : "C:/coursework/build",
		"source" : "C:/coursework"
	},
	"version" : 
	{
		"major" : 2,
		"minor" : 6
	}
}
